<config>
  <native xmlns="http://cisco.com/ns/yang/Cisco-IOS-XE-native">
    <GigabitEthernet>
      <name>3</name>
      <keepalive>false</keepalive>
        <mop>
          <enabled>false</enabled>
          <sysid>false</sysid>
        </mop>
        <negotiation xmlns="http://cisco.com/ns/yang/Cisco-IOS-XE-ethernet">
          <auto>true</auto>
        </negotiation>
        <xconnect xmlns="http://cisco.com/ns/yang/Cisco-IOS-XE-l2vpn">
          <address>10.255.255.14</address>
          <vcid>34</vcid>
          <encapsulation>mpls</encapsulation>
          <pw-class>ETH-to-ETH</pw-class>
          </xconnect>
    </GigabitEthernet>
  </native>
</config>